LICENSE
MANIFEST.in
basesetup.py
setup.py
examples/.gitignore
examples/Clustering-Comparison.ipynb
examples/Fs-Peptide-command-line.ipynb
examples/Fs-Peptide-in-RAM.ipynb
examples/Fs-Peptide-with-Pipeline.ipynb
examples/Fs-Peptide-with-dataset.ipynb
examples/GMRQ-Model-Selection.ipynb
examples/LICENSE.md
examples/Ligand-Featurization.ipynb
examples/Ward-Clustering.ipynb
examples/tICA-vs-PCA.ipynb
examples/advanced/bayesian-msm.ipynb
examples/advanced/hmm-and-msm.ipynb
examples/advanced/implied-timescales.ipynb
examples/advanced/plot-tica-heatmap.ipynb
examples/advanced/quadwell-n-states.ipynb
examples/advanced/quadwell.ipynb
examples/advanced/uncertainty.ipynb
msmbuilder/__init__.py
msmbuilder/base.py
msmbuilder/cmdline.py
msmbuilder/dataset.py
msmbuilder/version.py
msmbuilder.egg-info/PKG-INFO
msmbuilder.egg-info/SOURCES.txt
msmbuilder.egg-info/dependency_links.txt
msmbuilder.egg-info/entry_points.txt
msmbuilder.egg-info/not-zip-safe
msmbuilder.egg-info/top_level.txt
msmbuilder/cluster/.gitignore
msmbuilder/cluster/__init__.py
msmbuilder/cluster/_kmedoids.pyx
msmbuilder/cluster/agglomerative.py
msmbuilder/cluster/apm.py
msmbuilder/cluster/base.py
msmbuilder/cluster/kcenters.py
msmbuilder/cluster/kmedoids.py
msmbuilder/cluster/minibatchkmedoids.py
msmbuilder/cluster/ndgrid.py
msmbuilder/cluster/regularspatial.py
msmbuilder/cluster/src/kmedoids.cc
msmbuilder/cluster/src/kmedoids.h
msmbuilder/commands/__init__.py
msmbuilder/commands/atom_indices.py
msmbuilder/commands/convert_chunked_project.py
msmbuilder/commands/example_datasets.py
msmbuilder/commands/featurizer.py
msmbuilder/commands/fit.py
msmbuilder/commands/fit_transform.py
msmbuilder/commands/implied_timescales.py
msmbuilder/commands/template_project.py
msmbuilder/commands/transform.py
msmbuilder/decomposition/.gitignore
msmbuilder/decomposition/__init__.py
msmbuilder/decomposition/_speigh.pyx
msmbuilder/decomposition/base.py
msmbuilder/decomposition/kernel_approximation.py
msmbuilder/decomposition/ksparsetica.py
msmbuilder/decomposition/ktica.py
msmbuilder/decomposition/pca.py
msmbuilder/decomposition/sparsetica.py
msmbuilder/decomposition/tica.py
msmbuilder/decomposition/utils.py
